agnitra/__init__.py
agnitra/cli.py
agnitra/py.typed
agnitra/sdk.py
agnitra/telemetry_collector.py
agnitra/_sdk/__init__.py
agnitra/_sdk/deps.py
agnitra/_sdk/model_loader.py
agnitra/_sdk/optimizer.py
agnitra/api/__init__.py
agnitra/api/app.py
agnitra/api/auth.py
agnitra/api/billing.py
agnitra/api/cli.py
agnitra/api/license_server.py
agnitra/api/marketplace.py
agnitra/api/metrics_logger.py
agnitra/api/notifications.py
agnitra/api/queue.py
agnitra/api/service.py
agnitra/benchmarks/__init__.py
agnitra/benchmarks/runner.py
agnitra/core/__init__.py
agnitra/core/billing/__init__.py
agnitra/core/billing/uplift.py
agnitra/core/ir/__init__.py
agnitra/core/ir/graph_extractor.py
agnitra/core/kernel/__init__.py
agnitra/core/kernel/kernel_generator.py
agnitra/core/kernel/examples/__init__.py
agnitra/core/kernel/examples/layer_norm_kernel.py
agnitra/core/kernel/examples/matmul_kernel.py
agnitra/core/kernel/examples/vector_add_kernel.py
agnitra/core/licensing/__init__.py
agnitra/core/licensing/gpu_tracker.py
agnitra/core/licensing/manager.py
agnitra/core/metering/__init__.py
agnitra/core/metering/usage_meter.py
agnitra/core/optimizer/__init__.py
agnitra/core/optimizer/llm_optimizer.py
agnitra/core/optimizer/openevolve_adapter.py
agnitra/core/optimizer/rl_optimizer.py
agnitra/core/rl/__init__.py
agnitra/core/rl/codex_guided.py
agnitra/core/runtime/__init__.py
agnitra/core/runtime/agent.py
agnitra/core/runtime/cache.py
agnitra/core/runtime/control_plane.py
agnitra/core/runtime/fingerprint.py
agnitra/core/runtime/oem.py
agnitra/core/runtime/runtime_patcher.py
agnitra/core/runtime/telemetry_client.py
agnitra/core/runtime/tuning.py
agnitra/core/telemetry/__init__.py
agnitra/core/telemetry/collector.py
agnitra/dashboard/__init__.py
agnitra/dashboard/app.py
agnitra/dashboard/cli.py
agnitra/dashboard/templates/dashboard.html
agnitra/demo/__init__.py
agnitra/demo/demo.py
cli/__init__.py
cli/main.py
cli/optimize.py
cli/profile.py
agnitra-0.1.0.dist-info/LICENSE
agnitra-0.1.0.dist-info/METADATA
agnitra-0.1.0.dist-info/WHEEL
agnitra-0.1.0.dist-info/entry_points.txt
agnitra-0.1.0.dist-info/top_level.txt
agnitra-0.1.0.dist-info/RECORD
