Metadata-Version: 2.1
Name: agnitra
Version: 0.1.0
Summary: Optimization SDK, CLI, and API for Agnitra's pay-per-optimization platform.
Home-page: https://github.com/agnitraai/agnitraai
Author: Agnitra Labs
Author-email: Agnitra Labs <support@agnitra.ai>
License: Apache License
Project-URL: Homepage, https://github.com/agnitraai/agnitraai
Project-URL: Documentation, https://github.com/agnitraai/agnitraai#readme
Project-URL: Repository, https://github.com/agnitraai/agnitraai
Project-URL: Issues, https://github.com/agnitraai/agnitraai/issues
Keywords: machine-learning,mlops,optimization,gpu,telemetry
Classifier: Development Status :: 4 - Beta
Classifier: Intended Audience :: Developers
Classifier: License :: OSI Approved :: Apache Software License
Classifier: Programming Language :: Python
Classifier: Programming Language :: Python :: 3
Classifier: Programming Language :: Python :: 3.8
Classifier: Programming Language :: Python :: 3.9
Classifier: Programming Language :: Python :: 3.10
Classifier: Programming Language :: Python :: 3.11
Classifier: Programming Language :: Python :: 3.12
Classifier: Topic :: Software Development :: Libraries
Classifier: Topic :: Scientific/Engineering :: Artificial Intelligence
Requires-Python: >=3.8
License-File: LICENSE
Requires-Dist: click >=8.0
Requires-Dist: starlette >=0.27.0
Requires-Dist: uvicorn >=0.22.0
Requires-Dist: jinja2 >=3.1.0
Requires-Dist: python-multipart >=0.0.6
Provides-Extra: marketplace
Requires-Dist: boto3 >=1.28.0 ; extra == 'marketplace'
Requires-Dist: httpx >=0.24.0 ; extra == 'marketplace'
Requires-Dist: google-auth >=2.23.0 ; extra == 'marketplace'
Requires-Dist: requests >=2.31.0 ; extra == 'marketplace'
Provides-Extra: nvml
Requires-Dist: pynvml >=11.0.0 ; extra == 'nvml'
Provides-Extra: openai
Requires-Dist: openai >=1.0.0 ; extra == 'openai'
Requires-Dist: httpx >=0.23 ; extra == 'openai'
Provides-Extra: rl
Requires-Dist: stable-baselines3 >=2.0 ; extra == 'rl'
Requires-Dist: gymnasium >=0.28 ; extra == 'rl'
